odoo/addons/sale_order_safe_commitment_date/README.rst
odoo/addons/sale_order_safe_commitment_date/__init__.py
odoo/addons/sale_order_safe_commitment_date/__manifest__.py
odoo/addons/sale_order_safe_commitment_date/i18n/es.po
odoo/addons/sale_order_safe_commitment_date/i18n/sale_order_safe_commitment_date.pot
odoo/addons/sale_order_safe_commitment_date/models/__init__.py
odoo/addons/sale_order_safe_commitment_date/models/sale_order.py
odoo/addons/sale_order_safe_commitment_date/readme/CONFIGURE.md
odoo/addons/sale_order_safe_commitment_date/readme/CONTEXT.md
odoo/addons/sale_order_safe_commitment_date/readme/CONTRIBUTORS.md
odoo/addons/sale_order_safe_commitment_date/readme/DESCRIPTION.md
odoo/addons/sale_order_safe_commitment_date/readme/ROADMAP.md
odoo/addons/sale_order_safe_commitment_date/readme/USAGE.md
odoo/addons/sale_order_safe_commitment_date/static/description/icon.png
odoo/addons/sale_order_safe_commitment_date/static/description/index.html
odoo/addons/sale_order_safe_commitment_date/tests/__init__.py
odoo/addons/sale_order_safe_commitment_date/tests/test_sale_order_safe_commitment_date.py
odoo/addons/sale_order_safe_commitment_date/views/sale_order_views.xml
odoo_addon_sale_order_safe_commitment_date-16.0.1.3.0.2.dist-info/METADATA
odoo_addon_sale_order_safe_commitment_date-16.0.1.3.0.2.dist-info/WHEEL
odoo_addon_sale_order_safe_commitment_date-16.0.1.3.0.2.dist-info/top_level.txt
odoo_addon_sale_order_safe_commitment_date-16.0.1.3.0.2.dist-info/RECORD
